aippy/Parameters.py
aippy/__init__.py
aippy/flask_basicauth_ex.py
aippy/homeTools.py
aip_py-0.0.4.dist-info/LICENSE
aip_py-0.0.4.dist-info/METADATA
aip_py-0.0.4.dist-info/WHEEL
aip_py-0.0.4.dist-info/top_level.txt
aip_py-0.0.4.dist-info/RECORD
