Metadata-Version: 2.1
Name: aip-py
Version: 0.0.4
Summary: A aip-py useful package
Author-email: Jack Li <lizhq08@gmail.com>
Project-URL: Homepage, https://github.com/lizhq/aip-py
Project-URL: Bug Tracker, https://github.com/lizhq/aip-py/issues
Classifier: Programming Language :: Python :: 3
Classifier: License :: OSI Approved :: MIT License
Classifier: Operating System :: OS Independent
Requires-Python: >=3.8
License-File: LICENSE
Requires-Dist: flask ~=3.0.0
Requires-Dist: flask-basicauth
Requires-Dist: Pillow ~=10.1.0
